<report><server /><tasks /><hosts><host><asset_id>92189</asset_id></host></hosts><vulnerabilities><vulner><title>Memory Corruption</title><short_description>A potential Memory Corruption was detected.</short_description><description>The application crashes upon exploit.</description><how_to_fix>Sanitize all user inputs and outputs.</how_to_fix><links>https://www.example.com/security-advisory</links><publication_date>2023-06-24</publication_date><cvss>0.3564340517334119</cvss><cvss3>5.516989115892136</cvss3><global_id>1024</global_id></vulner><vulner><title>Local File Inclusion</title><short_description>A potential Local File Inclusion was detected.</short_description><description>Unauthorized file access is possible.</description><how_to_fix>Utilize proper authentication and authorization mechanisms.</how_to_fix><links>https://www.example.com/security-advisory</links><publication_date>2023-06-25</publication_date><cvss>9.96998261798499</cvss><cvss3>6.791824102154437</cvss3><global_id>1000</global_id></vulner><vulner><title>Remote Code Execution</title><short_description>A potential Remote Code Execution was detected.</short_description><description>An attacker can execute arbitrary code.</description><how_to_fix>Restrict access to certain system calls or functions.</how_to_fix><links>https://www.example.com/security-advisory</links><publication_date>2023-06-23</publication_date><cvss>1.8098971620589865</cvss><cvss3>7.935472717541792</cvss3><global_id>1001</global_id></vulner><vulner><title>Path Traversal</title><short_description>A potential Path Traversal was detected.</short_description><description>Privilege escalation is possible.</description><how_to_fix>Sanitize all user inputs and outputs.</how_to_fix><links>https://www.example.com/security-advisory</links><publication_date>2023-06-12</publication_date><cvss>9.018048370603445</cvss><cvss3>4.3869455904005346</cvss3><global_id>1002</global_id></vulner><vulner><title>Path Traversal</title><short_description>A potential Path Traversal was detected.</short_description><description>An attacker can execute arbitrary code.</description><how_to_fix>Update to the latest version or apply the security patch.</how_to_fix><links>https://www.example.com/security-advisory</links><publication_date>2023-06-23</publication_date><cvss>2.733043418797564</cvss><cvss3>5.1106119216757815</cvss3><global_id>1003</global_id></vulner><vulner><title>Denial of Service</title><short_description>A potential Denial of Service was detected.</short_description><description>Sensitive data might be leaked.</description><how_to_fix>Update to the latest version or apply the security patch.</how_to_fix><links>https://www.example.com/security-advisory</links><publication_date>2023-06-07</publication_date><cvss>3.9330909044885165</cvss><cvss3>4.039247296542613</cvss3><global_id>1004</global_id></vulner><vulner><title>SQL Injection</title><short_description>A potential SQL Injection was detected.</short_description><description>The application exposes internal files.</description><how_to_fix>Utilize proper authentication and authorization mechanisms.</how_to_fix><links>https://www.example.com/security-advisory</links><publication_date>2023-06-10</publication_date><cvss>2.035084399449276</cvss><cvss3>3.8857881398077487</cvss3><global_id>1005</global_id></vulner><vulner><title>Denial of Service</title><short_description>A potential Denial of Service was detected.</short_description><description>Sensitive memory locations can be accessed.</description><how_to_fix>Restrict access to certain system calls or functions.</how_to_fix><links>https://www.example.com/security-advisory</links><publication_date>2023-06-13</publication_date><cvss>7.799325174913172</cvss><cvss3>2.970070009985762</cvss3><global_id>1006</global_id></vulner><vulner><title>SQL Injection</title><short_description>A potential SQL Injection was detected.</short_description><description>Unauthorized file access is possible.</description><how_to_fix>Ensure proper memory management techniques are applied.</how_to_fix><links>https://www.example.com/security-advisory</links><publication_date>2023-06-12</publication_date><cvss>0.7441522383353849</cvss><cvss3>0.20674818256695482</cvss3><global_id>1007</global_id></vulner><vulner><title>Denial of Service</title><short_description>A potential Denial of Service was detected.</short_description><description>The application crashes upon exploit.</description><how_to_fix>Update to the latest version or apply the security patch.</how_to_fix><links>https://www.example.com/security-advisory</links><publication_date>2023-06-17</publication_date><cvss>8.364532899223345</cvss><cvss3>5.849179048149891</cvss3><global_id>1008</global_id></vulner><vulner><title>SQL Injection</title><short_description>A potential SQL Injection was detected.</short_description><description>Sensitive data might be leaked.</description><how_to_fix>Restrict access to certain system calls or functions.</how_to_fix><links>https://www.example.com/security-advisory</links><publication_date>2023-06-04</publication_date><cvss>4.472453210547032</cvss><cvss3>9.44250944321849</cvss3><global_id>1009</global_id></vulner><vulner><title>Buffer Overflow</title><short_description>A potential Buffer Overflow was detected.</short_description><description>Sensitive data might be leaked.</description><how_to_fix>Sanitize all user inputs and outputs.</how_to_fix><links>https://www.example.com/security-advisory</links><publication_date>2023-06-16</publication_date><cvss>5.5572743299338425</cvss><cvss3>4.5416220030532735</cvss3><global_id>1010</global_id></vulner><vulner><title>SQL Injection</title><short_description>A potential SQL Injection was detected.</short_description><description>The application is susceptible to denial of service attacks.</description><how_to_fix>Limit the resources available to the application.</how_to_fix><links>https://www.example.com/security-advisory</links><publication_date>2023-06-17</publication_date><cvss>8.716024635630284</cvss><cvss3>2.18016746085305</cvss3><global_id>1011</global_id></vulner><vulner><title>Path Traversal</title><short_description>A potential Path Traversal was detected.</short_description><description>The application exposes internal files.</description><how_to_fix>Update to the latest version or apply the security patch.</how_to_fix><links>https://www.example.com/security-advisory</links><publication_date>2023-06-18</publication_date><cvss>7.041487385412374</cvss><cvss3>3.134557893699302</cvss3><global_id>1012</global_id></vulner><vulner><title>Remote Code Execution</title><short_description>A potential Remote Code Execution was detected.</short_description><description>The application exposes internal files.</description><how_to_fix>Ensure proper memory management techniques are applied.</how_to_fix><links>https://www.example.com/security-advisory</links><publication_date>2023-06-20</publication_date><cvss>6.458809452883872</cvss><cvss3>9.263288279038669</cvss3><global_id>1013</global_id></vulner><vulner><title>Path Traversal</title><short_description>A potential Path Traversal was detected.</short_description><description>The application crashes upon exploit.</description><how_to_fix>Limit the resources available to the application.</how_to_fix><links>https://www.example.com/security-advisory</links><publication_date>2023-06-14</publication_date><cvss>3.154256591466612</cvss><cvss3>2.8139119188507875</cvss3><global_id>1014</global_id></vulner><vulner><title>Denial of Service</title><short_description>A potential Denial of Service was detected.</short_description><description>The application crashes upon exploit.</description><how_to_fix>Limit the resources available to the application.</how_to_fix><links>https://www.example.com/security-advisory</links><publication_date>2023-06-25</publication_date><cvss>3.3694354172631558</cvss><cvss3>1.1167129816753885</cvss3><global_id>1015</global_id></vulner><vulner><title>Memory Corruption</title><short_description>A potential Memory Corruption was detected.</short_description><description>Privilege escalation is possible.</description><how_to_fix>Utilize proper authentication and authorization mechanisms.</how_to_fix><links>https://www.example.com/security-advisory</links><publication_date>2023-06-09</publication_date><cvss>7.5580491989677565</cvss><cvss3>0.13781282129091021</cvss3><global_id>1016</global_id></vulner><vulner><title>Memory Corruption</title><short_description>A potential Memory Corruption was detected.</short_description><description>Privilege escalation is possible.</description><how_to_fix>Restrict access to certain system calls or functions.</how_to_fix><links>https://www.example.com/security-advisory</links><publication_date>2023-06-08</publication_date><cvss>5.510448903780128</cvss><cvss3>8.453634553496167</cvss3><global_id>1017</global_id></vulner><vulner><title>Local File Inclusion</title><short_description>A potential Local File Inclusion was detected.</short_description><description>Sensitive memory locations can be accessed.</description><how_to_fix>Restrict access to certain system calls or functions.</how_to_fix><links>https://www.example.com/security-advisory</links><publication_date>2023-07-02</publication_date><cvss>8.897964015746691</cvss><cvss3>6.867007990063493</cvss3><global_id>1018</global_id></vulner><vulner><title>Local File Inclusion</title><short_description>A potential Local File Inclusion was detected.</short_description><description>Sensitive memory locations can be accessed.</description><how_to_fix>Restrict access to certain system calls or functions.</how_to_fix><links>https://www.example.com/security-advisory</links><publication_date>2023-07-04</publication_date><cvss>8.785149339559503</cvss><cvss3>2.3927513955124793</cvss3><global_id>1019</global_id></vulner><vulner><title>Buffer Overflow</title><short_description>A potential Buffer Overflow was detected.</short_description><description>Sensitive data might be leaked.</description><how_to_fix>Update to the latest version or apply the security patch.</how_to_fix><links>https://www.example.com/security-advisory</links><publication_date>2023-06-14</publication_date><cvss>3.9625330963285608</cvss><cvss3>2.8114784251823433</cvss3><global_id>1020</global_id></vulner><vulner><title>Cross-Site Scripting</title><short_description>A potential Cross-Site Scripting was detected.</short_description><description>An attacker can execute arbitrary code.</description><how_to_fix>Limit the resources available to the application.</how_to_fix><links>https://www.example.com/security-advisory</links><publication_date>2023-07-01</publication_date><cvss>6.469819364324463</cvss><cvss3>9.919519818129176</cvss3><global_id>1021</global_id></vulner><vulner><title>Denial of Service</title><short_description>A potential Denial of Service was detected.</short_description><description>Unauthorized file access is possible.</description><how_to_fix>Utilize proper authentication and authorization mechanisms.</how_to_fix><links>https://www.example.com/security-advisory</links><publication_date>2023-06-08</publication_date><cvss>2.8273649493011344</cvss><cvss3>9.966900637175478</cvss3><global_id>1022</global_id></vulner><vulner><title>SQL Injection</title><short_description>A potential SQL Injection was detected.</short_description><description>Sensitive memory locations can be accessed.</description><how_to_fix>Restrict access to certain system calls or functions.</how_to_fix><links>https://www.example.com/security-advisory</links><publication_date>2023-06-25</publication_date><cvss>4.107939700951565</cvss><cvss3>1.0916546261346616</cvss3><global_id>1023</global_id></vulner></vulnerabilities></report>