<report><server /><tasks /><hosts><host><asset_id>43794</asset_id></host></hosts><vulnerabilities><vulner><title>Buffer Overflow</title><short_description>A potential Buffer Overflow was detected.</short_description><description>An attacker can execute arbitrary code.</description><how_to_fix>Sanitize all user inputs and outputs.</how_to_fix><links>https://www.example.com/security-advisory</links><publication_date>2023-06-10</publication_date><cvss>4.445996804327988</cvss><cvss3>0.6678416531113007</cvss3><global_id>1024</global_id></vulner><vulner><title>SQL Injection</title><short_description>A potential SQL Injection was detected.</short_description><description>The application crashes upon exploit.</description><how_to_fix>Ensure proper memory management techniques are applied.</how_to_fix><links>https://www.example.com/security-advisory</links><publication_date>2023-06-28</publication_date><cvss>4.777963504561606</cvss><cvss3>3.6769760341114486</cvss3><global_id>1000</global_id></vulner><vulner><title>Path Traversal</title><short_description>A potential Path Traversal was detected.</short_description><description>Unauthorized file access is possible.</description><how_to_fix>Ensure proper memory management techniques are applied.</how_to_fix><links>https://www.example.com/security-advisory</links><publication_date>2023-06-15</publication_date><cvss>4.4723395429207535</cvss><cvss3>6.3927071733714955</cvss3><global_id>1001</global_id></vulner><vulner><title>Local File Inclusion</title><short_description>A potential Local File Inclusion was detected.</short_description><description>Sensitive data might be leaked.</description><how_to_fix>Restrict access to certain system calls or functions.</how_to_fix><links>https://www.example.com/security-advisory</links><publication_date>2023-06-05</publication_date><cvss>3.433507169303885</cvss><cvss3>9.34174720104464</cvss3><global_id>1002</global_id></vulner><vulner><title>Local File Inclusion</title><short_description>A potential Local File Inclusion was detected.</short_description><description>The application exposes internal files.</description><how_to_fix>Sanitize all user inputs and outputs.</how_to_fix><links>https://www.example.com/security-advisory</links><publication_date>2023-06-16</publication_date><cvss>0.5147425149392026</cvss><cvss3>8.573543449373538</cvss3><global_id>1003</global_id></vulner><vulner><title>SQL Injection</title><short_description>A potential SQL Injection was detected.</short_description><description>Unauthorized file access is possible.</description><how_to_fix>Utilize proper authentication and authorization mechanisms.</how_to_fix><links>https://www.example.com/security-advisory</links><publication_date>2023-06-17</publication_date><cvss>9.054132835991718</cvss><cvss3>4.289982733006047</cvss3><global_id>1004</global_id></vulner><vulner><title>Denial of Service</title><short_description>A potential Denial of Service was detected.</short_description><description>The application crashes upon exploit.</description><how_to_fix>Utilize proper authentication and authorization mechanisms.</how_to_fix><links>https://www.example.com/security-advisory</links><publication_date>2023-06-08</publication_date><cvss>3.8092602307375136</cvss><cvss3>2.284158963292432</cvss3><global_id>1005</global_id></vulner><vulner><title>Denial of Service</title><short_description>A potential Denial of Service was detected.</short_description><description>The application is susceptible to denial of service attacks.</description><how_to_fix>Utilize proper authentication and authorization mechanisms.</how_to_fix><links>https://www.example.com/security-advisory</links><publication_date>2023-06-18</publication_date><cvss>3.4246974123897234</cvss><cvss3>0.4462993888142852</cvss3><global_id>1006</global_id></vulner><vulner><title>Cross-Site Scripting</title><short_description>A potential Cross-Site Scripting was detected.</short_description><description>Sensitive data might be leaked.</description><how_to_fix>Restrict access to certain system calls or functions.</how_to_fix><links>https://www.example.com/security-advisory</links><publication_date>2023-06-06</publication_date><cvss>7.7297783109239955</cvss><cvss3>6.530642685446976</cvss3><global_id>1007</global_id></vulner><vulner><title>Buffer Overflow</title><short_description>A potential Buffer Overflow was detected.</short_description><description>Sensitive memory locations can be accessed.</description><how_to_fix>Sanitize all user inputs and outputs.</how_to_fix><links>https://www.example.com/security-advisory</links><publication_date>2023-06-09</publication_date><cvss>8.044742836504701</cvss><cvss3>7.813494738194146</cvss3><global_id>1008</global_id></vulner><vulner><title>Remote Code Execution</title><short_description>A potential Remote Code Execution was detected.</short_description><description>Unauthorized file access is possible.</description><how_to_fix>Sanitize all user inputs and outputs.</how_to_fix><links>https://www.example.com/security-advisory</links><publication_date>2023-06-07</publication_date><cvss>3.155039570041518</cvss><cvss3>2.6540189288789695</cvss3><global_id>1009</global_id></vulner><vulner><title>SQL Injection</title><short_description>A potential SQL Injection was detected.</short_description><description>Sensitive data might be leaked.</description><how_to_fix>Sanitize all user inputs and outputs.</how_to_fix><links>https://www.example.com/security-advisory</links><publication_date>2023-06-28</publication_date><cvss>8.235020288874765</cvss><cvss3>1.955925262661261</cvss3><global_id>1010</global_id></vulner><vulner><title>Cross-Site Scripting</title><short_description>A potential Cross-Site Scripting was detected.</short_description><description>The application is susceptible to denial of service attacks.</description><how_to_fix>Update to the latest version or apply the security patch.</how_to_fix><links>https://www.example.com/security-advisory</links><publication_date>2023-06-27</publication_date><cvss>0.805981668561575</cvss><cvss3>7.706904539457984</cvss3><global_id>1011</global_id></vulner><vulner><title>Cross-Site Scripting</title><short_description>A potential Cross-Site Scripting was detected.</short_description><description>The application crashes upon exploit.</description><how_to_fix>Utilize proper authentication and authorization mechanisms.</how_to_fix><links>https://www.example.com/security-advisory</links><publication_date>2023-06-09</publication_date><cvss>1.789939252135938</cvss><cvss3>1.7872908754664152</cvss3><global_id>1012</global_id></vulner><vulner><title>Remote Code Execution</title><short_description>A potential Remote Code Execution was detected.</short_description><description>Privilege escalation is possible.</description><how_to_fix>Sanitize all user inputs and outputs.</how_to_fix><links>https://www.example.com/security-advisory</links><publication_date>2023-06-28</publication_date><cvss>9.798863106319782</cvss><cvss3>1.7561718525556225</cvss3><global_id>1014</global_id></vulner><vulner><title>Local File Inclusion</title><short_description>A potential Local File Inclusion was detected.</short_description><description>The application crashes upon exploit.</description><how_to_fix>Update to the latest version or apply the security patch.</how_to_fix><links>https://www.example.com/security-advisory</links><publication_date>2023-06-29</publication_date><cvss>1.1840081552769122</cvss><cvss3>8.717829619132132</cvss3><global_id>1015</global_id></vulner><vulner><title>Local File Inclusion</title><short_description>A potential Local File Inclusion was detected.</short_description><description>Sensitive memory locations can be accessed.</description><how_to_fix>Limit the resources available to the application.</how_to_fix><links>https://www.example.com/security-advisory</links><publication_date>2023-06-15</publication_date><cvss>5.78150359969213</cvss><cvss3>2.8350622449103335</cvss3><global_id>1016</global_id></vulner><vulner><title>Buffer Overflow</title><short_description>A potential Buffer Overflow was detected.</short_description><description>Sensitive data might be leaked.</description><how_to_fix>Sanitize all user inputs and outputs.</how_to_fix><links>https://www.example.com/security-advisory</links><publication_date>2023-06-11</publication_date><cvss>1.6566429610563682</cvss><cvss3>0.2870297728809079</cvss3><global_id>1017</global_id></vulner><vulner><title>Local File Inclusion</title><short_description>A potential Local File Inclusion was detected.</short_description><description>Sensitive memory locations can be accessed.</description><how_to_fix>Update to the latest version or apply the security patch.</how_to_fix><links>https://www.example.com/security-advisory</links><publication_date>2023-06-06</publication_date><cvss>6.600242081713324</cvss><cvss3>0.7926037067449454</cvss3><global_id>1018</global_id></vulner><vulner><title>Memory Corruption</title><short_description>A potential Memory Corruption was detected.</short_description><description>The application is susceptible to denial of service attacks.</description><how_to_fix>Update to the latest version or apply the security patch.</how_to_fix><links>https://www.example.com/security-advisory</links><publication_date>2023-06-16</publication_date><cvss>9.799381588427813</cvss><cvss3>0.7809681645993416</cvss3><global_id>1019</global_id></vulner><vulner><title>Cross-Site Scripting</title><short_description>A potential Cross-Site Scripting was detected.</short_description><description>The application exposes internal files.</description><how_to_fix>Update to the latest version or apply the security patch.</how_to_fix><links>https://www.example.com/security-advisory</links><publication_date>2023-06-15</publication_date><cvss>3.4592654683860555</cvss><cvss3>6.851436396194498</cvss3><global_id>1020</global_id></vulner><vulner><title>Remote Code Execution</title><short_description>A potential Remote Code Execution was detected.</short_description><description>Sensitive data might be leaked.</description><how_to_fix>Update to the latest version or apply the security patch.</how_to_fix><links>https://www.example.com/security-advisory</links><publication_date>2023-06-24</publication_date><cvss>7.427860879973909</cvss><cvss3>6.640802909255408</cvss3><global_id>1021</global_id></vulner><vulner><title>Denial of Service</title><short_description>A potential Denial of Service was detected.</short_description><description>Sensitive data might be leaked.</description><how_to_fix>Sanitize all user inputs and outputs.</how_to_fix><links>https://www.example.com/security-advisory</links><publication_date>2023-06-11</publication_date><cvss>8.441992157033555</cvss><cvss3>2.794496720064653</cvss3><global_id>1022</global_id></vulner><vulner><title>Denial of Service</title><short_description>A potential Denial of Service was detected.</short_description><description>Sensitive data might be leaked.</description><how_to_fix>Limit the resources available to the application.</how_to_fix><links>https://www.example.com/security-advisory</links><publication_date>2023-06-15</publication_date><cvss>9.71752635008596</cvss><cvss3>8.063596426094527</cvss3><global_id>1023</global_id></vulner></vulnerabilities></report>