<report><server /><tasks /><hosts><host><asset_id>90250</asset_id></host></hosts><vulnerabilities><vulner><title>Memory Corruption</title><short_description>A potential Memory Corruption was detected.</short_description><description>The application is susceptible to denial of service attacks.</description><how_to_fix>Utilize proper authentication and authorization mechanisms.</how_to_fix><links>https://www.example.com/security-advisory</links><publication_date>2023-06-09</publication_date><cvss>2.6814825054036384</cvss><cvss3>9.809898470902175</cvss3><global_id>1024</global_id></vulner><vulner><title>Denial of Service</title><short_description>A potential Denial of Service was detected.</short_description><description>The application crashes upon exploit.</description><how_to_fix>Ensure proper memory management techniques are applied.</how_to_fix><links>https://www.example.com/security-advisory</links><publication_date>2023-06-30</publication_date><cvss>8.707229983188943</cvss><cvss3>8.1660296977421</cvss3><global_id>1000</global_id></vulner><vulner><title>Denial of Service</title><short_description>A potential Denial of Service was detected.</short_description><description>The application exposes internal files.</description><how_to_fix>Restrict access to certain system calls or functions.</how_to_fix><links>https://www.example.com/security-advisory</links><publication_date>2023-06-30</publication_date><cvss>7.277142906790478</cvss><cvss3>2.6159629965726205</cvss3><global_id>1001</global_id></vulner><vulner><title>SQL Injection</title><short_description>A potential SQL Injection was detected.</short_description><description>Privilege escalation is possible.</description><how_to_fix>Update to the latest version or apply the security patch.</how_to_fix><links>https://www.example.com/security-advisory</links><publication_date>2023-07-01</publication_date><cvss>3.227127848797413</cvss><cvss3>1.4939074543953945</cvss3><global_id>1002</global_id></vulner><vulner><title>Path Traversal</title><short_description>A potential Path Traversal was detected.</short_description><description>Privilege escalation is possible.</description><how_to_fix>Limit the resources available to the application.</how_to_fix><links>https://www.example.com/security-advisory</links><publication_date>2023-06-11</publication_date><cvss>7.623688928952305</cvss><cvss3>5.995637386030095</cvss3><global_id>1003</global_id></vulner><vulner><title>Memory Corruption</title><short_description>A potential Memory Corruption was detected.</short_description><description>Privilege escalation is possible.</description><how_to_fix>Limit the resources available to the application.</how_to_fix><links>https://www.example.com/security-advisory</links><publication_date>2023-06-19</publication_date><cvss>7.552992731455958</cvss><cvss3>3.7609408576035297</cvss3><global_id>1004</global_id></vulner><vulner><title>Local File Inclusion</title><short_description>A potential Local File Inclusion was detected.</short_description><description>Privilege escalation is possible.</description><how_to_fix>Limit the resources available to the application.</how_to_fix><links>https://www.example.com/security-advisory</links><publication_date>2023-06-19</publication_date><cvss>6.344053335960468</cvss><cvss3>2.0662504368898302</cvss3><global_id>1005</global_id></vulner><vulner><title>Denial of Service</title><short_description>A potential Denial of Service was detected.</short_description><description>Sensitive memory locations can be accessed.</description><how_to_fix>Utilize proper authentication and authorization mechanisms.</how_to_fix><links>https://www.example.com/security-advisory</links><publication_date>2023-06-28</publication_date><cvss>0.30196447885990074</cvss><cvss3>5.82244523075448</cvss3><global_id>1006</global_id></vulner><vulner><title>Local File Inclusion</title><short_description>A potential Local File Inclusion was detected.</short_description><description>The application crashes upon exploit.</description><how_to_fix>Restrict access to certain system calls or functions.</how_to_fix><links>https://www.example.com/security-advisory</links><publication_date>2023-06-04</publication_date><cvss>0.10511583029027327</cvss><cvss3>4.258341431009704</cvss3><global_id>1007</global_id></vulner><vulner><title>SQL Injection</title><short_description>A potential SQL Injection was detected.</short_description><description>The application exposes internal files.</description><how_to_fix>Ensure proper memory management techniques are applied.</how_to_fix><links>https://www.example.com/security-advisory</links><publication_date>2023-07-04</publication_date><cvss>4.184739550075545</cvss><cvss3>4.001858315889628</cvss3><global_id>1008</global_id></vulner><vulner><title>Buffer Overflow</title><short_description>A potential Buffer Overflow was detected.</short_description><description>Unauthorized file access is possible.</description><how_to_fix>Utilize proper authentication and authorization mechanisms.</how_to_fix><links>https://www.example.com/security-advisory</links><publication_date>2023-06-09</publication_date><cvss>9.147270103839102</cvss><cvss3>3.850225912699706</cvss3><global_id>1009</global_id></vulner><vulner><title>SQL Injection</title><short_description>A potential SQL Injection was detected.</short_description><description>The application is susceptible to denial of service attacks.</description><how_to_fix>Sanitize all user inputs and outputs.</how_to_fix><links>https://www.example.com/security-advisory</links><publication_date>2023-06-19</publication_date><cvss>5.991402730641537</cvss><cvss3>9.262694710965357</cvss3><global_id>1011</global_id></vulner><vulner><title>SQL Injection</title><short_description>A potential SQL Injection was detected.</short_description><description>An attacker can execute arbitrary code.</description><how_to_fix>Utilize proper authentication and authorization mechanisms.</how_to_fix><links>https://www.example.com/security-advisory</links><publication_date>2023-06-21</publication_date><cvss>4.059740249988558</cvss><cvss3>0.8457713811942569</cvss3><global_id>1012</global_id></vulner><vulner><title>Buffer Overflow</title><short_description>A potential Buffer Overflow was detected.</short_description><description>Privilege escalation is possible.</description><how_to_fix>Sanitize all user inputs and outputs.</how_to_fix><links>https://www.example.com/security-advisory</links><publication_date>2023-06-28</publication_date><cvss>5.909394797966944</cvss><cvss3>8.020754280784017</cvss3><global_id>1013</global_id></vulner><vulner><title>Denial of Service</title><short_description>A potential Denial of Service was detected.</short_description><description>Sensitive memory locations can be accessed.</description><how_to_fix>Limit the resources available to the application.</how_to_fix><links>https://www.example.com/security-advisory</links><publication_date>2023-06-21</publication_date><cvss>8.434126258334967</cvss><cvss3>2.893640481346136</cvss3><global_id>1014</global_id></vulner><vulner><title>Denial of Service</title><short_description>A potential Denial of Service was detected.</short_description><description>Sensitive memory locations can be accessed.</description><how_to_fix>Restrict access to certain system calls or functions.</how_to_fix><links>https://www.example.com/security-advisory</links><publication_date>2023-06-18</publication_date><cvss>2.13368024830479</cvss><cvss3>5.042358670703619</cvss3><global_id>1015</global_id></vulner><vulner><title>Local File Inclusion</title><short_description>A potential Local File Inclusion was detected.</short_description><description>The application is susceptible to denial of service attacks.</description><how_to_fix>Ensure proper memory management techniques are applied.</how_to_fix><links>https://www.example.com/security-advisory</links><publication_date>2023-06-30</publication_date><cvss>2.9995300407993097</cvss><cvss3>7.475411024097988</cvss3><global_id>1016</global_id></vulner><vulner><title>SQL Injection</title><short_description>A potential SQL Injection was detected.</short_description><description>Unauthorized file access is possible.</description><how_to_fix>Limit the resources available to the application.</how_to_fix><links>https://www.example.com/security-advisory</links><publication_date>2023-06-27</publication_date><cvss>3.050626864150956</cvss><cvss3>9.69160657566042</cvss3><global_id>1017</global_id></vulner><vulner><title>Remote Code Execution</title><short_description>A potential Remote Code Execution was detected.</short_description><description>The application is susceptible to denial of service attacks.</description><how_to_fix>Restrict access to certain system calls or functions.</how_to_fix><links>https://www.example.com/security-advisory</links><publication_date>2023-06-10</publication_date><cvss>6.092050029619744</cvss><cvss3>4.811378626461959</cvss3><global_id>1018</global_id></vulner><vulner><title>Memory Corruption</title><short_description>A potential Memory Corruption was detected.</short_description><description>An attacker can execute arbitrary code.</description><how_to_fix>Restrict access to certain system calls or functions.</how_to_fix><links>https://www.example.com/security-advisory</links><publication_date>2023-07-02</publication_date><cvss>0.29171228676205474</cvss><cvss3>8.853121400474537</cvss3><global_id>1019</global_id></vulner><vulner><title>Cross-Site Scripting</title><short_description>A potential Cross-Site Scripting was detected.</short_description><description>The application crashes upon exploit.</description><how_to_fix>Sanitize all user inputs and outputs.</how_to_fix><links>https://www.example.com/security-advisory</links><publication_date>2023-06-22</publication_date><cvss>1.3792046963018767</cvss><cvss3>0.7557520111631821</cvss3><global_id>1020</global_id></vulner><vulner><title>Local File Inclusion</title><short_description>A potential Local File Inclusion was detected.</short_description><description>Privilege escalation is possible.</description><how_to_fix>Update to the latest version or apply the security patch.</how_to_fix><links>https://www.example.com/security-advisory</links><publication_date>2023-06-24</publication_date><cvss>1.0665120313373255</cvss><cvss3>9.681583935032265</cvss3><global_id>1022</global_id></vulner><vulner><title>Buffer Overflow</title><short_description>A potential Buffer Overflow was detected.</short_description><description>Sensitive memory locations can be accessed.</description><how_to_fix>Update to the latest version or apply the security patch.</how_to_fix><links>https://www.example.com/security-advisory</links><publication_date>2023-06-18</publication_date><cvss>0.9272877513099986</cvss><cvss3>5.570827133222669</cvss3><global_id>1023</global_id></vulner></vulnerabilities></report>