<report><server /><tasks /><hosts><host><asset_id>54999</asset_id></host></hosts><vulnerabilities><vulner><title>Remote Code Execution</title><short_description>A potential Remote Code Execution was detected.</short_description><description>The application is susceptible to denial of service attacks.</description><how_to_fix>Ensure proper memory management techniques are applied.</how_to_fix><links>https://www.example.com/security-advisory</links><publication_date>2023-07-02</publication_date><cvss>0.64551455960415</cvss><cvss3>6.327968817558832</cvss3><global_id>1024</global_id></vulner><vulner><title>Denial of Service</title><short_description>A potential Denial of Service was detected.</short_description><description>Unauthorized file access is possible.</description><how_to_fix>Sanitize all user inputs and outputs.</how_to_fix><links>https://www.example.com/security-advisory</links><publication_date>2023-06-16</publication_date><cvss>7.533906527118389</cvss><cvss3>5.20343951205818</cvss3><global_id>1000</global_id></vulner><vulner><title>Local File Inclusion</title><short_description>A potential Local File Inclusion was detected.</short_description><description>Sensitive memory locations can be accessed.</description><how_to_fix>Sanitize all user inputs and outputs.</how_to_fix><links>https://www.example.com/security-advisory</links><publication_date>2023-06-07</publication_date><cvss>9.787750025993178</cvss><cvss3>8.984510332205877</cvss3><global_id>1001</global_id></vulner><vulner><title>Remote Code Execution</title><short_description>A potential Remote Code Execution was detected.</short_description><description>An attacker can execute arbitrary code.</description><how_to_fix>Update to the latest version or apply the security patch.</how_to_fix><links>https://www.example.com/security-advisory</links><publication_date>2023-06-14</publication_date><cvss>9.78385268295178</cvss><cvss3>4.144948854211675</cvss3><global_id>1002</global_id></vulner><vulner><title>SQL Injection</title><short_description>A potential SQL Injection was detected.</short_description><description>The application exposes internal files.</description><how_to_fix>Limit the resources available to the application.</how_to_fix><links>https://www.example.com/security-advisory</links><publication_date>2023-06-04</publication_date><cvss>3.30311331755858</cvss><cvss3>4.513600785121237</cvss3><global_id>1003</global_id></vulner><vulner><title>Cross-Site Scripting</title><short_description>A potential Cross-Site Scripting was detected.</short_description><description>Privilege escalation is possible.</description><how_to_fix>Sanitize all user inputs and outputs.</how_to_fix><links>https://www.example.com/security-advisory</links><publication_date>2023-06-23</publication_date><cvss>7.6774241344980325</cvss><cvss3>9.726178132525558</cvss3><global_id>1004</global_id></vulner><vulner><title>SQL Injection</title><short_description>A potential SQL Injection was detected.</short_description><description>An attacker can execute arbitrary code.</description><how_to_fix>Sanitize all user inputs and outputs.</how_to_fix><links>https://www.example.com/security-advisory</links><publication_date>2023-06-19</publication_date><cvss>9.20001230863089</cvss><cvss3>2.6485892044498396</cvss3><global_id>1005</global_id></vulner><vulner><title>Denial of Service</title><short_description>A potential Denial of Service was detected.</short_description><description>The application exposes internal files.</description><how_to_fix>Limit the resources available to the application.</how_to_fix><links>https://www.example.com/security-advisory</links><publication_date>2023-06-05</publication_date><cvss>8.868836064725908</cvss><cvss3>7.4540477169695745</cvss3><global_id>1006</global_id></vulner><vulner><title>Cross-Site Scripting</title><short_description>A potential Cross-Site Scripting was detected.</short_description><description>Privilege escalation is possible.</description><how_to_fix>Ensure proper memory management techniques are applied.</how_to_fix><links>https://www.example.com/security-advisory</links><publication_date>2023-06-18</publication_date><cvss>0.7769820850936537</cvss><cvss3>1.336455008629781</cvss3><global_id>1007</global_id></vulner><vulner><title>Buffer Overflow</title><short_description>A potential Buffer Overflow was detected.</short_description><description>The application exposes internal files.</description><how_to_fix>Restrict access to certain system calls or functions.</how_to_fix><links>https://www.example.com/security-advisory</links><publication_date>2023-07-03</publication_date><cvss>1.1265062674894966</cvss><cvss3>2.0012226043393966</cvss3><global_id>1008</global_id></vulner><vulner><title>Local File Inclusion</title><short_description>A potential Local File Inclusion was detected.</short_description><description>The application crashes upon exploit.</description><how_to_fix>Sanitize all user inputs and outputs.</how_to_fix><links>https://www.example.com/security-advisory</links><publication_date>2023-07-01</publication_date><cvss>5.037665399568495</cvss><cvss3>2.113497604975997</cvss3><global_id>1009</global_id></vulner><vulner><title>Cross-Site Scripting</title><short_description>A potential Cross-Site Scripting was detected.</short_description><description>The application is susceptible to denial of service attacks.</description><how_to_fix>Sanitize all user inputs and outputs.</how_to_fix><links>https://www.example.com/security-advisory</links><publication_date>2023-06-28</publication_date><cvss>4.924962449407553</cvss><cvss3>1.7545118075132171</cvss3><global_id>1010</global_id></vulner><vulner><title>Remote Code Execution</title><short_description>A potential Remote Code Execution was detected.</short_description><description>An attacker can execute arbitrary code.</description><how_to_fix>Utilize proper authentication and authorization mechanisms.</how_to_fix><links>https://www.example.com/security-advisory</links><publication_date>2023-06-25</publication_date><cvss>0.30449556734733707</cvss><cvss3>4.459950609773184</cvss3><global_id>1011</global_id></vulner><vulner><title>Denial of Service</title><short_description>A potential Denial of Service was detected.</short_description><description>Sensitive memory locations can be accessed.</description><how_to_fix>Utilize proper authentication and authorization mechanisms.</how_to_fix><links>https://www.example.com/security-advisory</links><publication_date>2023-06-13</publication_date><cvss>9.581244608749977</cvss><cvss3>7.401175873888436</cvss3><global_id>1012</global_id></vulner><vulner><title>Buffer Overflow</title><short_description>A potential Buffer Overflow was detected.</short_description><description>Sensitive memory locations can be accessed.</description><how_to_fix>Utilize proper authentication and authorization mechanisms.</how_to_fix><links>https://www.example.com/security-advisory</links><publication_date>2023-06-13</publication_date><cvss>8.210658298876854</cvss><cvss3>7.1883447249894346</cvss3><global_id>1013</global_id></vulner><vulner><title>Remote Code Execution</title><short_description>A potential Remote Code Execution was detected.</short_description><description>The application crashes upon exploit.</description><how_to_fix>Ensure proper memory management techniques are applied.</how_to_fix><links>https://www.example.com/security-advisory</links><publication_date>2023-06-10</publication_date><cvss>3.404743780055016</cvss><cvss3>8.92665463526249</cvss3><global_id>1014</global_id></vulner><vulner><title>Buffer Overflow</title><short_description>A potential Buffer Overflow was detected.</short_description><description>An attacker can execute arbitrary code.</description><how_to_fix>Utilize proper authentication and authorization mechanisms.</how_to_fix><links>https://www.example.com/security-advisory</links><publication_date>2023-06-13</publication_date><cvss>4.688875321716798</cvss><cvss3>9.609256901057705</cvss3><global_id>1015</global_id></vulner><vulner><title>SQL Injection</title><short_description>A potential SQL Injection was detected.</short_description><description>Sensitive data might be leaked.</description><how_to_fix>Ensure proper memory management techniques are applied.</how_to_fix><links>https://www.example.com/security-advisory</links><publication_date>2023-06-29</publication_date><cvss>8.54942279418545</cvss><cvss3>8.530818576482579</cvss3><global_id>1016</global_id></vulner><vulner><title>SQL Injection</title><short_description>A potential SQL Injection was detected.</short_description><description>Sensitive memory locations can be accessed.</description><how_to_fix>Limit the resources available to the application.</how_to_fix><links>https://www.example.com/security-advisory</links><publication_date>2023-06-26</publication_date><cvss>0.6991361115343697</cvss><cvss3>8.81898335747225</cvss3><global_id>1017</global_id></vulner><vulner><title>Path Traversal</title><short_description>A potential Path Traversal was detected.</short_description><description>Sensitive memory locations can be accessed.</description><how_to_fix>Utilize proper authentication and authorization mechanisms.</how_to_fix><links>https://www.example.com/security-advisory</links><publication_date>2023-06-21</publication_date><cvss>4.924923227221152</cvss><cvss3>2.429993196586838</cvss3><global_id>1018</global_id></vulner><vulner><title>Buffer Overflow</title><short_description>A potential Buffer Overflow was detected.</short_description><description>An attacker can execute arbitrary code.</description><how_to_fix>Limit the resources available to the application.</how_to_fix><links>https://www.example.com/security-advisory</links><publication_date>2023-06-18</publication_date><cvss>4.664923532169574</cvss><cvss3>0.5781112646689768</cvss3><global_id>1019</global_id></vulner><vulner><title>SQL Injection</title><short_description>A potential SQL Injection was detected.</short_description><description>An attacker can execute arbitrary code.</description><how_to_fix>Limit the resources available to the application.</how_to_fix><links>https://www.example.com/security-advisory</links><publication_date>2023-06-11</publication_date><cvss>5.654352145031759</cvss><cvss3>6.616896218271579</cvss3><global_id>1020</global_id></vulner><vulner><title>Local File Inclusion</title><short_description>A potential Local File Inclusion was detected.</short_description><description>The application crashes upon exploit.</description><how_to_fix>Utilize proper authentication and authorization mechanisms.</how_to_fix><links>https://www.example.com/security-advisory</links><publication_date>2023-06-17</publication_date><cvss>5.528615212777112</cvss><cvss3>0.5352572143553092</cvss3><global_id>1021</global_id></vulner><vulner><title>Path Traversal</title><short_description>A potential Path Traversal was detected.</short_description><description>The application is susceptible to denial of service attacks.</description><how_to_fix>Restrict access to certain system calls or functions.</how_to_fix><links>https://www.example.com/security-advisory</links><publication_date>2023-06-10</publication_date><cvss>2.3515407946771107</cvss><cvss3>9.075963820612508</cvss3><global_id>1022</global_id></vulner><vulner><title>Path Traversal</title><short_description>A potential Path Traversal was detected.</short_description><description>Privilege escalation is possible.</description><how_to_fix>Update to the latest version or apply the security patch.</how_to_fix><links>https://www.example.com/security-advisory</links><publication_date>2023-06-15</publication_date><cvss>8.853046866719161</cvss><cvss3>5.381329286686314</cvss3><global_id>1023</global_id></vulner></vulnerabilities></report>