<report><server /><tasks /><hosts><host><asset_id>76787</asset_id></host></hosts><vulnerabilities><vulner><title>Cross-Site Scripting</title><short_description>A potential Cross-Site Scripting was detected.</short_description><description>The application crashes upon exploit.</description><how_to_fix>Utilize proper authentication and authorization mechanisms.</how_to_fix><links>https://www.example.com/security-advisory</links><publication_date>2023-06-25</publication_date><cvss>6.126094943288068</cvss><cvss3>7.366662019685839</cvss3><global_id>1024</global_id></vulner><vulner><title>Denial of Service</title><short_description>A potential Denial of Service was detected.</short_description><description>The application exposes internal files.</description><how_to_fix>Update to the latest version or apply the security patch.</how_to_fix><links>https://www.example.com/security-advisory</links><publication_date>2023-06-06</publication_date><cvss>1.4411019765237154</cvss><cvss3>8.592444690235189</cvss3><global_id>1000</global_id></vulner><vulner><title>Path Traversal</title><short_description>A potential Path Traversal was detected.</short_description><description>Privilege escalation is possible.</description><how_to_fix>Restrict access to certain system calls or functions.</how_to_fix><links>https://www.example.com/security-advisory</links><publication_date>2023-06-18</publication_date><cvss>3.7416632903599325</cvss><cvss3>0.7464987068231421</cvss3><global_id>1001</global_id></vulner><vulner><title>Cross-Site Scripting</title><short_description>A potential Cross-Site Scripting was detected.</short_description><description>Unauthorized file access is possible.</description><how_to_fix>Sanitize all user inputs and outputs.</how_to_fix><links>https://www.example.com/security-advisory</links><publication_date>2023-06-06</publication_date><cvss>5.960061095778801</cvss><cvss3>6.860304206602573</cvss3><global_id>1002</global_id></vulner><vulner><title>Cross-Site Scripting</title><short_description>A potential Cross-Site Scripting was detected.</short_description><description>Privilege escalation is possible.</description><how_to_fix>Limit the resources available to the application.</how_to_fix><links>https://www.example.com/security-advisory</links><publication_date>2023-06-26</publication_date><cvss>9.237705580186661</cvss><cvss3>6.501081548111426</cvss3><global_id>1003</global_id></vulner><vulner><title>Buffer Overflow</title><short_description>A potential Buffer Overflow was detected.</short_description><description>Privilege escalation is possible.</description><how_to_fix>Sanitize all user inputs and outputs.</how_to_fix><links>https://www.example.com/security-advisory</links><publication_date>2023-06-18</publication_date><cvss>0.03423415796648399</cvss><cvss3>9.372964656275492</cvss3><global_id>1004</global_id></vulner><vulner><title>Denial of Service</title><short_description>A potential Denial of Service was detected.</short_description><description>The application crashes upon exploit.</description><how_to_fix>Utilize proper authentication and authorization mechanisms.</how_to_fix><links>https://www.example.com/security-advisory</links><publication_date>2023-06-28</publication_date><cvss>9.769061554335114</cvss><cvss3>0.39625698156785627</cvss3><global_id>1005</global_id></vulner><vulner><title>Local File Inclusion</title><short_description>A potential Local File Inclusion was detected.</short_description><description>An attacker can execute arbitrary code.</description><how_to_fix>Ensure proper memory management techniques are applied.</how_to_fix><links>https://www.example.com/security-advisory</links><publication_date>2023-06-17</publication_date><cvss>3.2807920770325314</cvss><cvss3>0.180888262428619</cvss3><global_id>1006</global_id></vulner><vulner><title>Local File Inclusion</title><short_description>A potential Local File Inclusion was detected.</short_description><description>The application is susceptible to denial of service attacks.</description><how_to_fix>Ensure proper memory management techniques are applied.</how_to_fix><links>https://www.example.com/security-advisory</links><publication_date>2023-06-08</publication_date><cvss>4.547786991076163</cvss><cvss3>8.216774718221092</cvss3><global_id>1007</global_id></vulner><vulner><title>Denial of Service</title><short_description>A potential Denial of Service was detected.</short_description><description>The application is susceptible to denial of service attacks.</description><how_to_fix>Limit the resources available to the application.</how_to_fix><links>https://www.example.com/security-advisory</links><publication_date>2023-06-20</publication_date><cvss>6.385175387949182</cvss><cvss3>0.06937112936825307</cvss3><global_id>1008</global_id></vulner><vulner><title>Memory Corruption</title><short_description>A potential Memory Corruption was detected.</short_description><description>Sensitive data might be leaked.</description><how_to_fix>Limit the resources available to the application.</how_to_fix><links>https://www.example.com/security-advisory</links><publication_date>2023-06-27</publication_date><cvss>9.49597219637972</cvss><cvss3>6.378942773455611</cvss3><global_id>1009</global_id></vulner><vulner><title>Cross-Site Scripting</title><short_description>A potential Cross-Site Scripting was detected.</short_description><description>Privilege escalation is possible.</description><how_to_fix>Utilize proper authentication and authorization mechanisms.</how_to_fix><links>https://www.example.com/security-advisory</links><publication_date>2023-06-17</publication_date><cvss>6.092997105731339</cvss><cvss3>9.348868726217106</cvss3><global_id>1011</global_id></vulner><vulner><title>Remote Code Execution</title><short_description>A potential Remote Code Execution was detected.</short_description><description>Unauthorized file access is possible.</description><how_to_fix>Utilize proper authentication and authorization mechanisms.</how_to_fix><links>https://www.example.com/security-advisory</links><publication_date>2023-06-18</publication_date><cvss>4.109990597199298</cvss><cvss3>2.9420355454252443</cvss3><global_id>1012</global_id></vulner><vulner><title>Local File Inclusion</title><short_description>A potential Local File Inclusion was detected.</short_description><description>Unauthorized file access is possible.</description><how_to_fix>Update to the latest version or apply the security patch.</how_to_fix><links>https://www.example.com/security-advisory</links><publication_date>2023-06-19</publication_date><cvss>1.649232443455978</cvss><cvss3>1.9250443503380454</cvss3><global_id>1013</global_id></vulner><vulner><title>Memory Corruption</title><short_description>A potential Memory Corruption was detected.</short_description><description>Unauthorized file access is possible.</description><how_to_fix>Sanitize all user inputs and outputs.</how_to_fix><links>https://www.example.com/security-advisory</links><publication_date>2023-06-12</publication_date><cvss>3.671487469393544</cvss><cvss3>9.493847028885506</cvss3><global_id>1014</global_id></vulner><vulner><title>Denial of Service</title><short_description>A potential Denial of Service was detected.</short_description><description>The application is susceptible to denial of service attacks.</description><how_to_fix>Limit the resources available to the application.</how_to_fix><links>https://www.example.com/security-advisory</links><publication_date>2023-06-06</publication_date><cvss>6.952671366213875</cvss><cvss3>1.662108872543</cvss3><global_id>1015</global_id></vulner><vulner><title>Remote Code Execution</title><short_description>A potential Remote Code Execution was detected.</short_description><description>Privilege escalation is possible.</description><how_to_fix>Update to the latest version or apply the security patch.</how_to_fix><links>https://www.example.com/security-advisory</links><publication_date>2023-06-25</publication_date><cvss>9.782538955581057</cvss><cvss3>0.5803592332662433</cvss3><global_id>1016</global_id></vulner><vulner><title>Memory Corruption</title><short_description>A potential Memory Corruption was detected.</short_description><description>The application crashes upon exploit.</description><how_to_fix>Utilize proper authentication and authorization mechanisms.</how_to_fix><links>https://www.example.com/security-advisory</links><publication_date>2023-06-28</publication_date><cvss>1.6731062938758057</cvss><cvss3>5.796644860897107</cvss3><global_id>1017</global_id></vulner><vulner><title>Local File Inclusion</title><short_description>A potential Local File Inclusion was detected.</short_description><description>Privilege escalation is possible.</description><how_to_fix>Restrict access to certain system calls or functions.</how_to_fix><links>https://www.example.com/security-advisory</links><publication_date>2023-07-02</publication_date><cvss>6.124785872990706</cvss><cvss3>6.140072983817237</cvss3><global_id>1018</global_id></vulner><vulner><title>Memory Corruption</title><short_description>A potential Memory Corruption was detected.</short_description><description>The application exposes internal files.</description><how_to_fix>Utilize proper authentication and authorization mechanisms.</how_to_fix><links>https://www.example.com/security-advisory</links><publication_date>2023-06-20</publication_date><cvss>3.2471367578371235</cvss><cvss3>6.8797802008000675</cvss3><global_id>1019</global_id></vulner><vulner><title>Remote Code Execution</title><short_description>A potential Remote Code Execution was detected.</short_description><description>Unauthorized file access is possible.</description><how_to_fix>Utilize proper authentication and authorization mechanisms.</how_to_fix><links>https://www.example.com/security-advisory</links><publication_date>2023-06-06</publication_date><cvss>1.8997423922025158</cvss><cvss3>4.2353683392120605</cvss3><global_id>1020</global_id></vulner><vulner><title>Denial of Service</title><short_description>A potential Denial of Service was detected.</short_description><description>The application is susceptible to denial of service attacks.</description><how_to_fix>Ensure proper memory management techniques are applied.</how_to_fix><links>https://www.example.com/security-advisory</links><publication_date>2023-06-05</publication_date><cvss>1.2285404272260703</cvss><cvss3>6.102243482928397</cvss3><global_id>1021</global_id></vulner><vulner><title>Cross-Site Scripting</title><short_description>A potential Cross-Site Scripting was detected.</short_description><description>The application crashes upon exploit.</description><how_to_fix>Limit the resources available to the application.</how_to_fix><links>https://www.example.com/security-advisory</links><publication_date>2023-06-19</publication_date><cvss>2.8123436255084497</cvss><cvss3>1.223550840187183</cvss3><global_id>1023</global_id></vulner></vulnerabilities></report>