<report><server /><tasks /><hosts><host><asset_id>87241</asset_id></host></hosts><vulnerabilities><vulner><title>Remote Code Execution</title><short_description>A potential Remote Code Execution was detected.</short_description><description>Privilege escalation is possible.</description><how_to_fix>Ensure proper memory management techniques are applied.</how_to_fix><links>https://www.example.com/security-advisory</links><publication_date>2023-06-27</publication_date><cvss>7.888393383843875</cvss><cvss3>7.961998250234663</cvss3><global_id>1024</global_id></vulner><vulner><title>SQL Injection</title><short_description>A potential SQL Injection was detected.</short_description><description>Sensitive memory locations can be accessed.</description><how_to_fix>Limit the resources available to the application.</how_to_fix><links>https://www.example.com/security-advisory</links><publication_date>2023-07-02</publication_date><cvss>0.987736450476262</cvss><cvss3>6.147600981289669</cvss3><global_id>1000</global_id></vulner><vulner><title>Path Traversal</title><short_description>A potential Path Traversal was detected.</short_description><description>Privilege escalation is possible.</description><how_to_fix>Update to the latest version or apply the security patch.</how_to_fix><links>https://www.example.com/security-advisory</links><publication_date>2023-06-28</publication_date><cvss>9.573632551506117</cvss><cvss3>5.178423302430079</cvss3><global_id>1001</global_id></vulner><vulner><title>Memory Corruption</title><short_description>A potential Memory Corruption was detected.</short_description><description>The application crashes upon exploit.</description><how_to_fix>Sanitize all user inputs and outputs.</how_to_fix><links>https://www.example.com/security-advisory</links><publication_date>2023-06-23</publication_date><cvss>4.643869860673545</cvss><cvss3>8.137464898573732</cvss3><global_id>1002</global_id></vulner><vulner><title>Denial of Service</title><short_description>A potential Denial of Service was detected.</short_description><description>An attacker can execute arbitrary code.</description><how_to_fix>Limit the resources available to the application.</how_to_fix><links>https://www.example.com/security-advisory</links><publication_date>2023-06-24</publication_date><cvss>1.5499646094421282</cvss><cvss3>1.3961839654234165</cvss3><global_id>1003</global_id></vulner><vulner><title>Denial of Service</title><short_description>A potential Denial of Service was detected.</short_description><description>Privilege escalation is possible.</description><how_to_fix>Utilize proper authentication and authorization mechanisms.</how_to_fix><links>https://www.example.com/security-advisory</links><publication_date>2023-06-25</publication_date><cvss>6.982242135892024</cvss><cvss3>9.339252619260721</cvss3><global_id>1004</global_id></vulner><vulner><title>SQL Injection</title><short_description>A potential SQL Injection was detected.</short_description><description>Privilege escalation is possible.</description><how_to_fix>Ensure proper memory management techniques are applied.</how_to_fix><links>https://www.example.com/security-advisory</links><publication_date>2023-06-23</publication_date><cvss>4.022331257382082</cvss><cvss3>9.333121690650792</cvss3><global_id>1005</global_id></vulner><vulner><title>Local File Inclusion</title><short_description>A potential Local File Inclusion was detected.</short_description><description>Privilege escalation is possible.</description><how_to_fix>Restrict access to certain system calls or functions.</how_to_fix><links>https://www.example.com/security-advisory</links><publication_date>2023-06-15</publication_date><cvss>1.8506499028119872</cvss><cvss3>9.493061262791414</cvss3><global_id>1006</global_id></vulner><vulner><title>SQL Injection</title><short_description>A potential SQL Injection was detected.</short_description><description>Privilege escalation is possible.</description><how_to_fix>Update to the latest version or apply the security patch.</how_to_fix><links>https://www.example.com/security-advisory</links><publication_date>2023-06-04</publication_date><cvss>6.326847344327681</cvss><cvss3>7.8566523421175205</cvss3><global_id>1007</global_id></vulner><vulner><title>Buffer Overflow</title><short_description>A potential Buffer Overflow was detected.</short_description><description>Sensitive data might be leaked.</description><how_to_fix>Restrict access to certain system calls or functions.</how_to_fix><links>https://www.example.com/security-advisory</links><publication_date>2023-06-20</publication_date><cvss>4.793846014158212</cvss><cvss3>9.194251514618491</cvss3><global_id>1008</global_id></vulner><vulner><title>Cross-Site Scripting</title><short_description>A potential Cross-Site Scripting was detected.</short_description><description>Privilege escalation is possible.</description><how_to_fix>Update to the latest version or apply the security patch.</how_to_fix><links>https://www.example.com/security-advisory</links><publication_date>2023-06-28</publication_date><cvss>6.217414102903293</cvss><cvss3>0.7013908884983078</cvss3><global_id>1009</global_id></vulner><vulner><title>SQL Injection</title><short_description>A potential SQL Injection was detected.</short_description><description>Sensitive memory locations can be accessed.</description><how_to_fix>Limit the resources available to the application.</how_to_fix><links>https://www.example.com/security-advisory</links><publication_date>2023-06-08</publication_date><cvss>2.8602851582554467</cvss><cvss3>7.0447666378398335</cvss3><global_id>1010</global_id></vulner><vulner><title>Memory Corruption</title><short_description>A potential Memory Corruption was detected.</short_description><description>Unauthorized file access is possible.</description><how_to_fix>Restrict access to certain system calls or functions.</how_to_fix><links>https://www.example.com/security-advisory</links><publication_date>2023-07-04</publication_date><cvss>5.362613825810908</cvss><cvss3>7.247950798084288</cvss3><global_id>1011</global_id></vulner><vulner><title>Cross-Site Scripting</title><short_description>A potential Cross-Site Scripting was detected.</short_description><description>The application crashes upon exploit.</description><how_to_fix>Restrict access to certain system calls or functions.</how_to_fix><links>https://www.example.com/security-advisory</links><publication_date>2023-06-19</publication_date><cvss>5.111538649478197</cvss><cvss3>2.2704449065141263</cvss3><global_id>1012</global_id></vulner><vulner><title>Local File Inclusion</title><short_description>A potential Local File Inclusion was detected.</short_description><description>Sensitive data might be leaked.</description><how_to_fix>Sanitize all user inputs and outputs.</how_to_fix><links>https://www.example.com/security-advisory</links><publication_date>2023-06-27</publication_date><cvss>1.7750925778215798</cvss><cvss3>9.985714967845833</cvss3><global_id>1013</global_id></vulner><vulner><title>Remote Code Execution</title><short_description>A potential Remote Code Execution was detected.</short_description><description>Privilege escalation is possible.</description><how_to_fix>Update to the latest version or apply the security patch.</how_to_fix><links>https://www.example.com/security-advisory</links><publication_date>2023-07-02</publication_date><cvss>9.648730582414448</cvss><cvss3>4.980717383929316</cvss3><global_id>1016</global_id></vulner><vulner><title>Path Traversal</title><short_description>A potential Path Traversal was detected.</short_description><description>The application is susceptible to denial of service attacks.</description><how_to_fix>Ensure proper memory management techniques are applied.</how_to_fix><links>https://www.example.com/security-advisory</links><publication_date>2023-06-14</publication_date><cvss>1.4499179057232114</cvss><cvss3>3.282617237289184</cvss3><global_id>1017</global_id></vulner><vulner><title>Buffer Overflow</title><short_description>A potential Buffer Overflow was detected.</short_description><description>Unauthorized file access is possible.</description><how_to_fix>Utilize proper authentication and authorization mechanisms.</how_to_fix><links>https://www.example.com/security-advisory</links><publication_date>2023-06-26</publication_date><cvss>5.01009177361778</cvss><cvss3>0.6518447996582399</cvss3><global_id>1018</global_id></vulner><vulner><title>SQL Injection</title><short_description>A potential SQL Injection was detected.</short_description><description>The application crashes upon exploit.</description><how_to_fix>Limit the resources available to the application.</how_to_fix><links>https://www.example.com/security-advisory</links><publication_date>2023-06-13</publication_date><cvss>1.7680536006233316</cvss><cvss3>2.2648416234863156</cvss3><global_id>1019</global_id></vulner><vulner><title>Buffer Overflow</title><short_description>A potential Buffer Overflow was detected.</short_description><description>An attacker can execute arbitrary code.</description><how_to_fix>Ensure proper memory management techniques are applied.</how_to_fix><links>https://www.example.com/security-advisory</links><publication_date>2023-06-08</publication_date><cvss>1.840104339063563</cvss><cvss3>9.197643668505947</cvss3><global_id>1021</global_id></vulner><vulner><title>Denial of Service</title><short_description>A potential Denial of Service was detected.</short_description><description>The application is susceptible to denial of service attacks.</description><how_to_fix>Ensure proper memory management techniques are applied.</how_to_fix><links>https://www.example.com/security-advisory</links><publication_date>2023-06-29</publication_date><cvss>7.676211034724425</cvss><cvss3>0.8555983716152338</cvss3><global_id>1022</global_id></vulner><vulner><title>Buffer Overflow</title><short_description>A potential Buffer Overflow was detected.</short_description><description>An attacker can execute arbitrary code.</description><how_to_fix>Update to the latest version or apply the security patch.</how_to_fix><links>https://www.example.com/security-advisory</links><publication_date>2023-07-02</publication_date><cvss>4.309520484842336</cvss><cvss3>0.5253646322474514</cvss3><global_id>1023</global_id></vulner></vulnerabilities></report>