<report><server /><tasks /><hosts><host><asset_id>28423</asset_id></host></hosts><vulnerabilities><vulner><title>SQL Injection</title><short_description>A potential SQL Injection was detected.</short_description><description>Unauthorized file access is possible.</description><how_to_fix>Utilize proper authentication and authorization mechanisms.</how_to_fix><links>https://www.example.com/security-advisory</links><publication_date>2023-06-30</publication_date><cvss>3.395231633741634</cvss><cvss3>1.2025562975065063</cvss3><global_id>1024</global_id></vulner><vulner><title>Denial of Service</title><short_description>A potential Denial of Service was detected.</short_description><description>Privilege escalation is possible.</description><how_to_fix>Update to the latest version or apply the security patch.</how_to_fix><links>https://www.example.com/security-advisory</links><publication_date>2023-06-07</publication_date><cvss>3.6639648434540115</cvss><cvss3>0.3105078672764183</cvss3><global_id>1000</global_id></vulner><vulner><title>Denial of Service</title><short_description>A potential Denial of Service was detected.</short_description><description>Privilege escalation is possible.</description><how_to_fix>Limit the resources available to the application.</how_to_fix><links>https://www.example.com/security-advisory</links><publication_date>2023-06-28</publication_date><cvss>9.706694477551743</cvss><cvss3>6.535549154425922</cvss3><global_id>1001</global_id></vulner><vulner><title>Cross-Site Scripting</title><short_description>A potential Cross-Site Scripting was detected.</short_description><description>Unauthorized file access is possible.</description><how_to_fix>Restrict access to certain system calls or functions.</how_to_fix><links>https://www.example.com/security-advisory</links><publication_date>2023-06-25</publication_date><cvss>9.324770253657146</cvss><cvss3>6.040238018614119</cvss3><global_id>1002</global_id></vulner><vulner><title>Remote Code Execution</title><short_description>A potential Remote Code Execution was detected.</short_description><description>Privilege escalation is possible.</description><how_to_fix>Restrict access to certain system calls or functions.</how_to_fix><links>https://www.example.com/security-advisory</links><publication_date>2023-06-27</publication_date><cvss>2.005783411974712</cvss><cvss3>7.043523441619132</cvss3><global_id>1003</global_id></vulner><vulner><title>Cross-Site Scripting</title><short_description>A potential Cross-Site Scripting was detected.</short_description><description>Sensitive data might be leaked.</description><how_to_fix>Limit the resources available to the application.</how_to_fix><links>https://www.example.com/security-advisory</links><publication_date>2023-06-05</publication_date><cvss>3.839660357278577</cvss><cvss3>5.2251591168456635</cvss3><global_id>1004</global_id></vulner><vulner><title>Path Traversal</title><short_description>A potential Path Traversal was detected.</short_description><description>Sensitive memory locations can be accessed.</description><how_to_fix>Utilize proper authentication and authorization mechanisms.</how_to_fix><links>https://www.example.com/security-advisory</links><publication_date>2023-06-14</publication_date><cvss>3.5262776229070933</cvss><cvss3>7.185663767371953</cvss3><global_id>1005</global_id></vulner><vulner><title>Denial of Service</title><short_description>A potential Denial of Service was detected.</short_description><description>The application exposes internal files.</description><how_to_fix>Ensure proper memory management techniques are applied.</how_to_fix><links>https://www.example.com/security-advisory</links><publication_date>2023-06-15</publication_date><cvss>3.67471373547044</cvss><cvss3>1.114525670533969</cvss3><global_id>1006</global_id></vulner><vulner><title>Remote Code Execution</title><short_description>A potential Remote Code Execution was detected.</short_description><description>Privilege escalation is possible.</description><how_to_fix>Update to the latest version or apply the security patch.</how_to_fix><links>https://www.example.com/security-advisory</links><publication_date>2023-06-08</publication_date><cvss>1.7834391356994306</cvss><cvss3>7.054104901956033</cvss3><global_id>1007</global_id></vulner><vulner><title>Denial of Service</title><short_description>A potential Denial of Service was detected.</short_description><description>An attacker can execute arbitrary code.</description><how_to_fix>Update to the latest version or apply the security patch.</how_to_fix><links>https://www.example.com/security-advisory</links><publication_date>2023-07-03</publication_date><cvss>4.284633756941325</cvss><cvss3>2.8757231335914035</cvss3><global_id>1008</global_id></vulner><vulner><title>Path Traversal</title><short_description>A potential Path Traversal was detected.</short_description><description>Sensitive memory locations can be accessed.</description><how_to_fix>Restrict access to certain system calls or functions.</how_to_fix><links>https://www.example.com/security-advisory</links><publication_date>2023-07-03</publication_date><cvss>3.5890064841769576</cvss><cvss3>9.112765642879651</cvss3><global_id>1009</global_id></vulner><vulner><title>Local File Inclusion</title><short_description>A potential Local File Inclusion was detected.</short_description><description>The application exposes internal files.</description><how_to_fix>Update to the latest version or apply the security patch.</how_to_fix><links>https://www.example.com/security-advisory</links><publication_date>2023-06-26</publication_date><cvss>4.86097763399362</cvss><cvss3>9.317510350337459</cvss3><global_id>1010</global_id></vulner><vulner><title>SQL Injection</title><short_description>A potential SQL Injection was detected.</short_description><description>Unauthorized file access is possible.</description><how_to_fix>Sanitize all user inputs and outputs.</how_to_fix><links>https://www.example.com/security-advisory</links><publication_date>2023-06-26</publication_date><cvss>9.535118111070979</cvss><cvss3>0.6350447469798381</cvss3><global_id>1011</global_id></vulner><vulner><title>Remote Code Execution</title><short_description>A potential Remote Code Execution was detected.</short_description><description>The application exposes internal files.</description><how_to_fix>Sanitize all user inputs and outputs.</how_to_fix><links>https://www.example.com/security-advisory</links><publication_date>2023-06-29</publication_date><cvss>4.227437822540667</cvss><cvss3>6.001209230908183</cvss3><global_id>1012</global_id></vulner><vulner><title>SQL Injection</title><short_description>A potential SQL Injection was detected.</short_description><description>An attacker can execute arbitrary code.</description><how_to_fix>Update to the latest version or apply the security patch.</how_to_fix><links>https://www.example.com/security-advisory</links><publication_date>2023-06-19</publication_date><cvss>6.527488771909955</cvss><cvss3>9.121160374422157</cvss3><global_id>1013</global_id></vulner><vulner><title>SQL Injection</title><short_description>A potential SQL Injection was detected.</short_description><description>An attacker can execute arbitrary code.</description><how_to_fix>Restrict access to certain system calls or functions.</how_to_fix><links>https://www.example.com/security-advisory</links><publication_date>2023-06-17</publication_date><cvss>8.18941470514064</cvss><cvss3>9.689326601163943</cvss3><global_id>1014</global_id></vulner><vulner><title>Path Traversal</title><short_description>A potential Path Traversal was detected.</short_description><description>Unauthorized file access is possible.</description><how_to_fix>Update to the latest version or apply the security patch.</how_to_fix><links>https://www.example.com/security-advisory</links><publication_date>2023-06-28</publication_date><cvss>7.003403977100539</cvss><cvss3>1.2072931658302855</cvss3><global_id>1015</global_id></vulner><vulner><title>Local File Inclusion</title><short_description>A potential Local File Inclusion was detected.</short_description><description>The application exposes internal files.</description><how_to_fix>Limit the resources available to the application.</how_to_fix><links>https://www.example.com/security-advisory</links><publication_date>2023-06-04</publication_date><cvss>1.9371542684634835</cvss><cvss3>1.3070503804140143</cvss3><global_id>1016</global_id></vulner><vulner><title>Remote Code Execution</title><short_description>A potential Remote Code Execution was detected.</short_description><description>Sensitive data might be leaked.</description><how_to_fix>Limit the resources available to the application.</how_to_fix><links>https://www.example.com/security-advisory</links><publication_date>2023-06-16</publication_date><cvss>5.388607218973208</cvss><cvss3>0.3441932981847873</cvss3><global_id>1017</global_id></vulner><vulner><title>Memory Corruption</title><short_description>A potential Memory Corruption was detected.</short_description><description>The application is susceptible to denial of service attacks.</description><how_to_fix>Ensure proper memory management techniques are applied.</how_to_fix><links>https://www.example.com/security-advisory</links><publication_date>2023-06-23</publication_date><cvss>2.762209205735396</cvss><cvss3>2.4206508020624398</cvss3><global_id>1018</global_id></vulner><vulner><title>Remote Code Execution</title><short_description>A potential Remote Code Execution was detected.</short_description><description>Sensitive data might be leaked.</description><how_to_fix>Sanitize all user inputs and outputs.</how_to_fix><links>https://www.example.com/security-advisory</links><publication_date>2023-06-19</publication_date><cvss>9.829850826956854</cvss><cvss3>1.5675690568269163</cvss3><global_id>1019</global_id></vulner><vulner><title>Buffer Overflow</title><short_description>A potential Buffer Overflow was detected.</short_description><description>The application crashes upon exploit.</description><how_to_fix>Limit the resources available to the application.</how_to_fix><links>https://www.example.com/security-advisory</links><publication_date>2023-06-29</publication_date><cvss>4.19895711056845</cvss><cvss3>4.9367457895595415</cvss3><global_id>1020</global_id></vulner><vulner><title>Cross-Site Scripting</title><short_description>A potential Cross-Site Scripting was detected.</short_description><description>Unauthorized file access is possible.</description><how_to_fix>Limit the resources available to the application.</how_to_fix><links>https://www.example.com/security-advisory</links><publication_date>2023-06-14</publication_date><cvss>6.519489863043572</cvss><cvss3>4.059478282761834</cvss3><global_id>1021</global_id></vulner><vulner><title>Memory Corruption</title><short_description>A potential Memory Corruption was detected.</short_description><description>The application exposes internal files.</description><how_to_fix>Sanitize all user inputs and outputs.</how_to_fix><links>https://www.example.com/security-advisory</links><publication_date>2023-06-19</publication_date><cvss>3.2289679066673207</cvss><cvss3>6.110822561283138</cvss3><global_id>1022</global_id></vulner><vulner><title>Remote Code Execution</title><short_description>A potential Remote Code Execution was detected.</short_description><description>An attacker can execute arbitrary code.</description><how_to_fix>Limit the resources available to the application.</how_to_fix><links>https://www.example.com/security-advisory</links><publication_date>2023-06-04</publication_date><cvss>1.682159294165294</cvss><cvss3>2.8934314656379656</cvss3><global_id>1023</global_id></vulner></vulnerabilities></report>