<report><server /><tasks /><hosts><host><asset_id>38393</asset_id></host></hosts><vulnerabilities><vulner><title>SQL Injection</title><short_description>A potential SQL Injection was detected.</short_description><description>Unauthorized file access is possible.</description><how_to_fix>Update to the latest version or apply the security patch.</how_to_fix><links>https://www.example.com/security-advisory</links><publication_date>2023-06-07</publication_date><cvss>9.019045929042829</cvss><cvss3>4.399596789367539</cvss3><global_id>1024</global_id></vulner><vulner><title>Local File Inclusion</title><short_description>A potential Local File Inclusion was detected.</short_description><description>The application crashes upon exploit.</description><how_to_fix>Update to the latest version or apply the security patch.</how_to_fix><links>https://www.example.com/security-advisory</links><publication_date>2023-06-26</publication_date><cvss>4.838615158211729</cvss><cvss3>1.5663560728025383</cvss3><global_id>1000</global_id></vulner><vulner><title>Denial of Service</title><short_description>A potential Denial of Service was detected.</short_description><description>Sensitive memory locations can be accessed.</description><how_to_fix>Update to the latest version or apply the security patch.</how_to_fix><links>https://www.example.com/security-advisory</links><publication_date>2023-06-22</publication_date><cvss>5.094586665944496</cvss><cvss3>7.412702446763307</cvss3><global_id>1001</global_id></vulner><vulner><title>Path Traversal</title><short_description>A potential Path Traversal was detected.</short_description><description>An attacker can execute arbitrary code.</description><how_to_fix>Update to the latest version or apply the security patch.</how_to_fix><links>https://www.example.com/security-advisory</links><publication_date>2023-06-28</publication_date><cvss>8.623071110748125</cvss><cvss3>3.795948261769073</cvss3><global_id>1002</global_id></vulner><vulner><title>Memory Corruption</title><short_description>A potential Memory Corruption was detected.</short_description><description>Unauthorized file access is possible.</description><how_to_fix>Ensure proper memory management techniques are applied.</how_to_fix><links>https://www.example.com/security-advisory</links><publication_date>2023-06-10</publication_date><cvss>9.382692682663317</cvss><cvss3>5.584298680277383</cvss3><global_id>1003</global_id></vulner><vulner><title>SQL Injection</title><short_description>A potential SQL Injection was detected.</short_description><description>Unauthorized file access is possible.</description><how_to_fix>Utilize proper authentication and authorization mechanisms.</how_to_fix><links>https://www.example.com/security-advisory</links><publication_date>2023-06-10</publication_date><cvss>4.715317603397681</cvss><cvss3>5.596765851413928</cvss3><global_id>1004</global_id></vulner><vulner><title>Remote Code Execution</title><short_description>A potential Remote Code Execution was detected.</short_description><description>The application crashes upon exploit.</description><how_to_fix>Restrict access to certain system calls or functions.</how_to_fix><links>https://www.example.com/security-advisory</links><publication_date>2023-06-23</publication_date><cvss>3.2349332407243914</cvss><cvss3>2.771440152746989</cvss3><global_id>1005</global_id></vulner><vulner><title>Denial of Service</title><short_description>A potential Denial of Service was detected.</short_description><description>Sensitive memory locations can be accessed.</description><how_to_fix>Ensure proper memory management techniques are applied.</how_to_fix><links>https://www.example.com/security-advisory</links><publication_date>2023-07-03</publication_date><cvss>6.622962788248325</cvss><cvss3>6.018064679969724</cvss3><global_id>1006</global_id></vulner><vulner><title>Path Traversal</title><short_description>A potential Path Traversal was detected.</short_description><description>Sensitive memory locations can be accessed.</description><how_to_fix>Utilize proper authentication and authorization mechanisms.</how_to_fix><links>https://www.example.com/security-advisory</links><publication_date>2023-06-23</publication_date><cvss>0.3082937332424507</cvss><cvss3>7.98384386603558</cvss3><global_id>1007</global_id></vulner><vulner><title>Denial of Service</title><short_description>A potential Denial of Service was detected.</short_description><description>Sensitive data might be leaked.</description><how_to_fix>Utilize proper authentication and authorization mechanisms.</how_to_fix><links>https://www.example.com/security-advisory</links><publication_date>2023-06-26</publication_date><cvss>3.6958696900276387</cvss><cvss3>2.6557217589753135</cvss3><global_id>1008</global_id></vulner><vulner><title>Cross-Site Scripting</title><short_description>A potential Cross-Site Scripting was detected.</short_description><description>The application is susceptible to denial of service attacks.</description><how_to_fix>Utilize proper authentication and authorization mechanisms.</how_to_fix><links>https://www.example.com/security-advisory</links><publication_date>2023-06-27</publication_date><cvss>3.930347932603413</cvss><cvss3>8.075214324286438</cvss3><global_id>1009</global_id></vulner><vulner><title>Buffer Overflow</title><short_description>A potential Buffer Overflow was detected.</short_description><description>The application exposes internal files.</description><how_to_fix>Restrict access to certain system calls or functions.</how_to_fix><links>https://www.example.com/security-advisory</links><publication_date>2023-06-05</publication_date><cvss>3.6438870933504797</cvss><cvss3>6.958587745088716</cvss3><global_id>1010</global_id></vulner><vulner><title>Remote Code Execution</title><short_description>A potential Remote Code Execution was detected.</short_description><description>Privilege escalation is possible.</description><how_to_fix>Update to the latest version or apply the security patch.</how_to_fix><links>https://www.example.com/security-advisory</links><publication_date>2023-06-15</publication_date><cvss>2.412829447015593</cvss><cvss3>5.890593980978153</cvss3><global_id>1011</global_id></vulner><vulner><title>Path Traversal</title><short_description>A potential Path Traversal was detected.</short_description><description>Sensitive memory locations can be accessed.</description><how_to_fix>Sanitize all user inputs and outputs.</how_to_fix><links>https://www.example.com/security-advisory</links><publication_date>2023-06-08</publication_date><cvss>2.459823369256341</cvss><cvss3>5.892267713552178</cvss3><global_id>1012</global_id></vulner><vulner><title>Path Traversal</title><short_description>A potential Path Traversal was detected.</short_description><description>Unauthorized file access is possible.</description><how_to_fix>Limit the resources available to the application.</how_to_fix><links>https://www.example.com/security-advisory</links><publication_date>2023-06-27</publication_date><cvss>5.577757722139836</cvss><cvss3>1.5578762358508924</cvss3><global_id>1013</global_id></vulner><vulner><title>Path Traversal</title><short_description>A potential Path Traversal was detected.</short_description><description>Unauthorized file access is possible.</description><how_to_fix>Restrict access to certain system calls or functions.</how_to_fix><links>https://www.example.com/security-advisory</links><publication_date>2023-06-27</publication_date><cvss>3.5205619064285876</cvss><cvss3>1.045373161698674</cvss3><global_id>1014</global_id></vulner><vulner><title>Local File Inclusion</title><short_description>A potential Local File Inclusion was detected.</short_description><description>Sensitive data might be leaked.</description><how_to_fix>Utilize proper authentication and authorization mechanisms.</how_to_fix><links>https://www.example.com/security-advisory</links><publication_date>2023-06-05</publication_date><cvss>0.3384320900534288</cvss><cvss3>8.176860430522927</cvss3><global_id>1015</global_id></vulner><vulner><title>Denial of Service</title><short_description>A potential Denial of Service was detected.</short_description><description>Sensitive memory locations can be accessed.</description><how_to_fix>Sanitize all user inputs and outputs.</how_to_fix><links>https://www.example.com/security-advisory</links><publication_date>2023-06-23</publication_date><cvss>5.219983056139931</cvss><cvss3>8.811108461407487</cvss3><global_id>1016</global_id></vulner><vulner><title>Denial of Service</title><short_description>A potential Denial of Service was detected.</short_description><description>Sensitive data might be leaked.</description><how_to_fix>Sanitize all user inputs and outputs.</how_to_fix><links>https://www.example.com/security-advisory</links><publication_date>2023-06-27</publication_date><cvss>7.3168253260457785</cvss><cvss3>6.10370958174438</cvss3><global_id>1017</global_id></vulner><vulner><title>Memory Corruption</title><short_description>A potential Memory Corruption was detected.</short_description><description>The application crashes upon exploit.</description><how_to_fix>Update to the latest version or apply the security patch.</how_to_fix><links>https://www.example.com/security-advisory</links><publication_date>2023-06-07</publication_date><cvss>4.510278467132496</cvss><cvss3>9.507764719216658</cvss3><global_id>1018</global_id></vulner><vulner><title>SQL Injection</title><short_description>A potential SQL Injection was detected.</short_description><description>Sensitive memory locations can be accessed.</description><how_to_fix>Ensure proper memory management techniques are applied.</how_to_fix><links>https://www.example.com/security-advisory</links><publication_date>2023-07-04</publication_date><cvss>9.452148359744877</cvss><cvss3>9.633092150010782</cvss3><global_id>1019</global_id></vulner><vulner><title>Remote Code Execution</title><short_description>A potential Remote Code Execution was detected.</short_description><description>Privilege escalation is possible.</description><how_to_fix>Utilize proper authentication and authorization mechanisms.</how_to_fix><links>https://www.example.com/security-advisory</links><publication_date>2023-06-16</publication_date><cvss>1.28780681754602</cvss><cvss3>8.427281766612651</cvss3><global_id>1020</global_id></vulner><vulner><title>Cross-Site Scripting</title><short_description>A potential Cross-Site Scripting was detected.</short_description><description>Sensitive memory locations can be accessed.</description><how_to_fix>Ensure proper memory management techniques are applied.</how_to_fix><links>https://www.example.com/security-advisory</links><publication_date>2023-06-16</publication_date><cvss>0.2318149667336178</cvss><cvss3>5.305524950605292</cvss3><global_id>1021</global_id></vulner><vulner><title>SQL Injection</title><short_description>A potential SQL Injection was detected.</short_description><description>Sensitive data might be leaked.</description><how_to_fix>Update to the latest version or apply the security patch.</how_to_fix><links>https://www.example.com/security-advisory</links><publication_date>2023-06-23</publication_date><cvss>9.294171659142634</cvss><cvss3>9.762181010983074</cvss3><global_id>1022</global_id></vulner><vulner><title>Path Traversal</title><short_description>A potential Path Traversal was detected.</short_description><description>An attacker can execute arbitrary code.</description><how_to_fix>Update to the latest version or apply the security patch.</how_to_fix><links>https://www.example.com/security-advisory</links><publication_date>2023-06-12</publication_date><cvss>0.28495864504811785</cvss><cvss3>0.9149211841716265</cvss3><global_id>1023</global_id></vulner></vulnerabilities></report>