<report><server /><tasks /><hosts><host><asset_id>55731</asset_id></host></hosts><vulnerabilities><vulner><title>Buffer Overflow</title><short_description>A potential Buffer Overflow was detected.</short_description><description>An attacker can execute arbitrary code.</description><how_to_fix>Sanitize all user inputs and outputs.</how_to_fix><links>https://www.example.com/security-advisory</links><publication_date>2023-06-22</publication_date><cvss>9.346865552428898</cvss><cvss3>9.65185851095948</cvss3><global_id>1024</global_id></vulner><vulner><title>SQL Injection</title><short_description>A potential SQL Injection was detected.</short_description><description>Sensitive data might be leaked.</description><how_to_fix>Update to the latest version or apply the security patch.</how_to_fix><links>https://www.example.com/security-advisory</links><publication_date>2023-06-04</publication_date><cvss>9.950862376174225</cvss><cvss3>5.016355530812774</cvss3><global_id>1000</global_id></vulner><vulner><title>Path Traversal</title><short_description>A potential Path Traversal was detected.</short_description><description>Sensitive data might be leaked.</description><how_to_fix>Utilize proper authentication and authorization mechanisms.</how_to_fix><links>https://www.example.com/security-advisory</links><publication_date>2023-06-06</publication_date><cvss>4.47906860390593</cvss><cvss3>1.8159708442854938</cvss3><global_id>1001</global_id></vulner><vulner><title>Cross-Site Scripting</title><short_description>A potential Cross-Site Scripting was detected.</short_description><description>Sensitive data might be leaked.</description><how_to_fix>Ensure proper memory management techniques are applied.</how_to_fix><links>https://www.example.com/security-advisory</links><publication_date>2023-06-14</publication_date><cvss>3.8288659013396376</cvss><cvss3>3.2137905407401313</cvss3><global_id>1002</global_id></vulner><vulner><title>Path Traversal</title><short_description>A potential Path Traversal was detected.</short_description><description>Sensitive data might be leaked.</description><how_to_fix>Ensure proper memory management techniques are applied.</how_to_fix><links>https://www.example.com/security-advisory</links><publication_date>2023-06-13</publication_date><cvss>6.860456461062729</cvss><cvss3>0.11307239783123646</cvss3><global_id>1003</global_id></vulner><vulner><title>Denial of Service</title><short_description>A potential Denial of Service was detected.</short_description><description>Privilege escalation is possible.</description><how_to_fix>Utilize proper authentication and authorization mechanisms.</how_to_fix><links>https://www.example.com/security-advisory</links><publication_date>2023-07-01</publication_date><cvss>8.309916472145938</cvss><cvss3>7.532703178040967</cvss3><global_id>1004</global_id></vulner><vulner><title>Remote Code Execution</title><short_description>A potential Remote Code Execution was detected.</short_description><description>Sensitive memory locations can be accessed.</description><how_to_fix>Ensure proper memory management techniques are applied.</how_to_fix><links>https://www.example.com/security-advisory</links><publication_date>2023-06-20</publication_date><cvss>7.128017222420592</cvss><cvss3>3.175144958919275</cvss3><global_id>1005</global_id></vulner><vulner><title>Buffer Overflow</title><short_description>A potential Buffer Overflow was detected.</short_description><description>Privilege escalation is possible.</description><how_to_fix>Ensure proper memory management techniques are applied.</how_to_fix><links>https://www.example.com/security-advisory</links><publication_date>2023-06-04</publication_date><cvss>8.665005952639875</cvss><cvss3>1.4513098207007913</cvss3><global_id>1007</global_id></vulner><vulner><title>SQL Injection</title><short_description>A potential SQL Injection was detected.</short_description><description>The application crashes upon exploit.</description><how_to_fix>Restrict access to certain system calls or functions.</how_to_fix><links>https://www.example.com/security-advisory</links><publication_date>2023-06-07</publication_date><cvss>4.577974663474041</cvss><cvss3>5.761243745214964</cvss3><global_id>1008</global_id></vulner><vulner><title>Denial of Service</title><short_description>A potential Denial of Service was detected.</short_description><description>The application crashes upon exploit.</description><how_to_fix>Sanitize all user inputs and outputs.</how_to_fix><links>https://www.example.com/security-advisory</links><publication_date>2023-06-21</publication_date><cvss>6.1844716510996705</cvss><cvss3>1.6582833369959515</cvss3><global_id>1010</global_id></vulner><vulner><title>Local File Inclusion</title><short_description>A potential Local File Inclusion was detected.</short_description><description>Sensitive data might be leaked.</description><how_to_fix>Restrict access to certain system calls or functions.</how_to_fix><links>https://www.example.com/security-advisory</links><publication_date>2023-06-28</publication_date><cvss>2.2104816880924893</cvss><cvss3>3.6689838151716545</cvss3><global_id>1012</global_id></vulner><vulner><title>Local File Inclusion</title><short_description>A potential Local File Inclusion was detected.</short_description><description>Privilege escalation is possible.</description><how_to_fix>Utilize proper authentication and authorization mechanisms.</how_to_fix><links>https://www.example.com/security-advisory</links><publication_date>2023-06-28</publication_date><cvss>4.642733823085788</cvss><cvss3>6.133743683612271</cvss3><global_id>1013</global_id></vulner><vulner><title>Remote Code Execution</title><short_description>A potential Remote Code Execution was detected.</short_description><description>Privilege escalation is possible.</description><how_to_fix>Utilize proper authentication and authorization mechanisms.</how_to_fix><links>https://www.example.com/security-advisory</links><publication_date>2023-06-10</publication_date><cvss>2.280802632418376</cvss><cvss3>2.261647094238708</cvss3><global_id>1014</global_id></vulner><vulner><title>Memory Corruption</title><short_description>A potential Memory Corruption was detected.</short_description><description>The application crashes upon exploit.</description><how_to_fix>Utilize proper authentication and authorization mechanisms.</how_to_fix><links>https://www.example.com/security-advisory</links><publication_date>2023-06-13</publication_date><cvss>8.55851049783366</cvss><cvss3>4.094643419950945</cvss3><global_id>1015</global_id></vulner><vulner><title>Path Traversal</title><short_description>A potential Path Traversal was detected.</short_description><description>The application crashes upon exploit.</description><how_to_fix>Sanitize all user inputs and outputs.</how_to_fix><links>https://www.example.com/security-advisory</links><publication_date>2023-07-02</publication_date><cvss>8.523775766903958</cvss><cvss3>7.361383642484859</cvss3><global_id>1016</global_id></vulner><vulner><title>Cross-Site Scripting</title><short_description>A potential Cross-Site Scripting was detected.</short_description><description>Privilege escalation is possible.</description><how_to_fix>Limit the resources available to the application.</how_to_fix><links>https://www.example.com/security-advisory</links><publication_date>2023-06-08</publication_date><cvss>8.605375449577595</cvss><cvss3>2.377362240368772</cvss3><global_id>1017</global_id></vulner><vulner><title>Denial of Service</title><short_description>A potential Denial of Service was detected.</short_description><description>The application exposes internal files.</description><how_to_fix>Update to the latest version or apply the security patch.</how_to_fix><links>https://www.example.com/security-advisory</links><publication_date>2023-07-02</publication_date><cvss>6.799387692380718</cvss><cvss3>5.2980534986022985</cvss3><global_id>1018</global_id></vulner><vulner><title>Buffer Overflow</title><short_description>A potential Buffer Overflow was detected.</short_description><description>Privilege escalation is possible.</description><how_to_fix>Ensure proper memory management techniques are applied.</how_to_fix><links>https://www.example.com/security-advisory</links><publication_date>2023-06-11</publication_date><cvss>8.997945808691112</cvss><cvss3>7.675189329613261</cvss3><global_id>1019</global_id></vulner><vulner><title>SQL Injection</title><short_description>A potential SQL Injection was detected.</short_description><description>Sensitive data might be leaked.</description><how_to_fix>Utilize proper authentication and authorization mechanisms.</how_to_fix><links>https://www.example.com/security-advisory</links><publication_date>2023-06-12</publication_date><cvss>5.687954492292699</cvss><cvss3>4.34978704187877</cvss3><global_id>1020</global_id></vulner><vulner><title>SQL Injection</title><short_description>A potential SQL Injection was detected.</short_description><description>Unauthorized file access is possible.</description><how_to_fix>Restrict access to certain system calls or functions.</how_to_fix><links>https://www.example.com/security-advisory</links><publication_date>2023-07-02</publication_date><cvss>3.9573706647814277</cvss><cvss3>5.916143112353536</cvss3><global_id>1021</global_id></vulner><vulner><title>Remote Code Execution</title><short_description>A potential Remote Code Execution was detected.</short_description><description>Sensitive memory locations can be accessed.</description><how_to_fix>Update to the latest version or apply the security patch.</how_to_fix><links>https://www.example.com/security-advisory</links><publication_date>2023-07-02</publication_date><cvss>1.5414112377701428</cvss><cvss3>4.643199244065648</cvss3><global_id>1022</global_id></vulner><vulner><title>Memory Corruption</title><short_description>A potential Memory Corruption was detected.</short_description><description>The application crashes upon exploit.</description><how_to_fix>Sanitize all user inputs and outputs.</how_to_fix><links>https://www.example.com/security-advisory</links><publication_date>2023-06-17</publication_date><cvss>1.9130630489267642</cvss><cvss3>7.280429154721897</cvss3><global_id>1023</global_id></vulner></vulnerabilities></report>